{
  "id": 5000743,
  "name": "黑暗火锅仪式",
  "text": "探入更深的黑暗，用血肉增幅魔力。",
  "tips": "",
  "mapping_id": 8001269,
  "once_new": 0,
  "round_number": 1,
  "waiting_round": 1,
  "waiting_round_end_action": [],
  "method_settlement": "",
  "auto_begin": 0,
  "auto_result": 0,
  "location": "黑街:[1,9]",
  "icon": "rite_21",
  "tag_tips": [],
  "tag_tips_up": {},
  "tips_text": [
    "能永久增强享用者的对应属性。",
    "祭品可以是任何角色，属性越好，效果越好。",
    "仪式必定成功，唯一的需求就是祭品。",
    "只有密教徒或拥有黑暗知识的人才能享用祭品。"
  ],
  "open_conditions": [],
  "random_text": {},
  "random_text_up": {},
  "random_effect": {},
  "settlement_prior": [],
  "settlement": [
    {
      "guid": "1fb9437d-eecc-4c98-8cf5-120cef4a942c",
      "condition": {
        "!s2": 1,
        "!s3": 1,
        "!s4": 1,
        "!s5": 1
      },
      "result_title": "",
      "result_text": "因为没有人准备享用，锅里的煮烂了，只好倒了。",
      "result": {
        "clean.s6": 1
      },
      "action": {}
    },
    {
      "guid": "bd18c995-118e-4898-87a4-2701b057cf87",
      "condition": {
        "any": {
          "s2": 1,
          "s3": 1,
          "s4": 1,
          "s5": 1
        }
      },
      "result_title": "",
      "result_text": "祭品在锅内唱着歌跳着舞，不一时就分离四散。",
      "result": {
        "clean.s6": 1
      },
      "action": {}
    }
  ],
  "settlement_extre": [
    {
      "guid": "c020d515-4357-4d74-b499-57d081a64cec",
      "condition": {
        "s2": 1,
        "s6.智慧>=": 5
      },
      "result_title": "",
      "result_text": "祭品的智慧化作享用者的智慧。",
      "result": {
        "s2+智慧": 3
      },
      "action": {}
    },
    {
      "guid": "67d99876-db06-4eba-8711-17ff3697544e",
      "condition": {
        "s2": 1,
        "s6.智慧>=": 3,
        "s6.智慧<": 5
      },
      "result_title": "",
      "result_text": "祭品的智慧化作享用者的智慧。",
      "result": {
        "s2+智慧": 2
      },
      "action": {}
    },
    {
      "guid": "c429cbc5-8daa-4ea1-97eb-7d41e19493e7",
      "condition": {
        "s2": 1,
        "s6.智慧>=": 1,
        "s6.智慧<": 3
      },
      "result_title": "",
      "result_text": "祭品的智慧化作享用者的智慧。",
      "result": {
        "s2+智慧": 1
      },
      "action": {}
    },
    {
      "guid": "385041f3-d624-472d-a09d-d71c3dc89f8f",
      "condition": {
        "s3": 1,
        "s6.魅力>=": 5
      },
      "result_title": "",
      "result_text": "祭品的魅力化作享用者的魅力。",
      "result": {
        "s3+魅力": 3
      },
      "action": {}
    },
    {
      "guid": "ec65d773-6a4b-4d59-a026-35a07bac3900",
      "condition": {
        "s3": 1,
        "s6.魅力>=": 3,
        "s6.魅力<": 5
      },
      "result_title": "",
      "result_text": "祭品的魅力化作享用者的魅力。",
      "result": {
        "s3+魅力": 2
      },
      "action": {}
    },
    {
      "guid": "66d847b9-9257-47f6-b74b-18098f79cce1",
      "condition": {
        "s3": 1,
        "s6.魅力>=": 1,
        "s6.魅力<": 3
      },
      "result_title": "",
      "result_text": "祭品的魅力化作享用者的魅力。",
      "result": {
        "s3+魅力": 1
      },
      "action": {}
    },
    {
      "guid": "886a6e3a-ae1d-435b-b455-464617520adc",
      "condition": {
        "any": {
          "s4": 1,
          "s5": 1
        },
        "s6.体魄>=": 5
      },
      "result_title": "",
      "result_text": "祭品的体魄化作享用者的体魄。",
      "result": {
        "s4+体魄": 3,
        "s5+体魄": 3
      },
      "action": {}
    },
    {
      "guid": "31584f74-4efd-45ad-85fa-6577625bb93a",
      "condition": {
        "any": {
          "s4": 1,
          "s5": 1
        },
        "s6.体魄>=": 3,
        "s6.体魄<": 5
      },
      "result_title": "",
      "result_text": "祭品的体魄化作享用者的体魄。",
      "result": {
        "s4+体魄": 2,
        "s5+体魄": 2
      },
      "action": {}
    },
    {
      "guid": "345ce7ec-d577-4818-8965-a5d3e61a12e9",
      "condition": {
        "any": {
          "s4": 1,
          "s5": 1
        },
        "s6.体魄>=": 1,
        "s6.体魄<": 3
      },
      "result_title": "",
      "result_text": "祭品的体魄化作享用者的体魄。",
      "result": {
        "s4+体魄": 1,
        "s5+体魄": 1
      },
      "action": {}
    }
  ],
  "cards_slot": {
    "s1": {
      "guid": "d3554d31-b3f9-40a5-93c8-0d5fea9d5889",
      "condition": {
        "is": 2000466
      },
      "open_adsorb": 1,
      "is_key": 0,
      "is_empty": 0,
      "is_enemy": 0,
      "text": "神秘的锅"
    },
    "s2": {
      "guid": "93946209-9e7c-45f6-b94e-7fbaa2fe758d",
      "condition": {
        "type": "char",
        "any": {
          "黑暗知识": 1,
          "密教徒": 1
        }
      },
      "open_adsorb": 0,
      "is_key": 0,
      "is_empty": 1,
      "is_enemy": 0,
      "text": "此人享用头部，智慧愈加丰盈。"
    },
    "s3": {
      "guid": "0236c80a-e344-497c-b13d-d6d0282469b8",
      "condition": {
        "type": "char",
        "any": {
          "黑暗知识": 1,
          "密教徒": 1
        }
      },
      "open_adsorb": 0,
      "is_key": 0,
      "is_empty": 1,
      "is_enemy": 0,
      "text": "此人享用内脏，魅力愈加照人。"
    },
    "s4": {
      "guid": "3326bf9f-2250-423f-908c-8332f7a47183",
      "condition": {
        "type": "char",
        "any": {
          "黑暗知识": 1,
          "密教徒": 1
        }
      },
      "open_adsorb": 0,
      "is_key": 0,
      "is_empty": 1,
      "is_enemy": 0,
      "text": "此人享用肉体，体魄愈加强壮。"
    },
    "s5": {
      "guid": "25e78681-fc96-4d48-a925-8b5d7fc5ea65",
      "condition": {
        "type": "char",
        "any": {
          "黑暗知识": 1,
          "密教徒": 1
        }
      },
      "open_adsorb": 0,
      "is_key": 0,
      "is_empty": 1,
      "is_enemy": 0,
      "text": "此人享用肉体，体魄愈加强壮。"
    },
    "s6": {
      "guid": "c2b59eba-759e-4836-8f88-611f9d970257",
      "condition": {
        "any": {
          "type": "char",
          "任意处置": 1
        },
        "!主角": 1,
        "!怪物": 1,
        "!动物": 1
      },
      "open_adsorb": 0,
      "is_key": 0,
      "is_empty": 0,
      "is_enemy": 0,
      "text": "此人被享用，魂飞魄散。"
    }
  }
}