{
  "id": 5006166,
  "name": "杀人检查",
  "text": "你……接受了小薇的祝福之后，有没有认真杀人啊？如果没有，小薇可就要生气咯？",
  "tips": "",
  "mapping_id": 8001002,
  "once_new": 0,
  "round_number": 1,
  "waiting_round": 1,
  "waiting_round_end_action": [],
  "method_settlement": "",
  "auto_begin": 1,
  "auto_result": 0,
  "location": "自宅:[2,12]",
  "icon": "rite_16",
  "tag_tips": [],
  "tag_tips_up": {},
  "tips_text": [
    "请经常使用小薇进行战斗，否则就会受到惩罚"
  ],
  "open_conditions": [],
  "random_text": {},
  "random_text_up": {},
  "settlement_prior": [],
  "settlement": [
    {
      "guid": "5cde17c7-429c-47a1-89e7-f87c98aed503",
      "condition": {
        "counter.7000875<": 1,
        "counter.7000863>=": 5
      },
      "result_title": "好，杀得好",
      "result_text": "妖精开心地在你面前摆出了一大堆收藏品——牙齿，指甲，眼珠子，挂着耳环的半截耳朵，哇，还有一片头皮！都是它在跟着你之后得到的好东西！[player.name]主人棒棒棒！杀杀杀！\n你能感觉到，在这种欢乐的情绪中，妖精的力量变强了……",
      "result": {
        "s1+重投": 1,
        "counter+7000875": 1,
        "counter=7000863": 0
      },
      "action": {}
    },
    {
      "guid": "c32ca40c-d190-4b2b-a003-c9e872b66f11",
      "condition": {
        "counter.7000875<": 1,
        "counter.7000863<": 5,
        "counter.7000863>=": 1
      },
      "result_title": "还不够啊……",
      "result_text": "小薇仿佛一个伤心的孩子，抱着自己的最心爱的玩具，在你的桌上打滚。“小薇还没有玩够嘛……”如果它怀里的宝贝不是一颗人的眼球，就更有说服力了……\n也许你之后可以试试满足它，毕竟，妖精是情绪的动物，当它高兴的时候，它的力量也会更强。",
      "result": {},
      "action": {}
    },
    {
      "guid": "ceb975bf-a008-4896-9c5d-28a4034874a5",
      "condition": {
        "counter.7000875<": 1,
        "counter.7000863<": 1,
        "counter.7000876<": 1
      },
      "result_title": "你敷衍我，我要闹了",
      "result_text": "小薇在你的头发缝隙中打滚，它渴望着杀戮与战斗！而你完全没有满足它一点点！它就要枯萎了！你能感觉到，随着情绪的低落，妖精的力量也在降低——而且现在它还会在你与人说话的时候，不停地在袍子下面做出猥琐的形状——啊，真是糟糕透了，这些妖精。",
      "result": {
        "s1-重投": 1,
        "s1-社交": 2,
        "counter+7000876": 1
      },
      "action": {}
    },
    {
      "guid": "878de2a8-f1a1-41e9-811b-1f46b9272671",
      "condition": {
        "counter.7000863<": 1,
        "counter.7000876>=": 1
      },
      "result_title": "你敷衍我，我要闹了",
      "result_text": "小薇在你的头发缝隙中打滚，它渴望着杀戮与战斗！而你完全没有满足它一点点！它就要枯萎了！你能感觉到，随着情绪的低落，妖精的力量也在降低——而且现在它还会在你与人说话的时候，不停地在袍子下面做出猥琐的形状——啊，真是糟糕透了，这些妖精。",
      "result": {},
      "action": {}
    },
    {
      "guid": "7889a9a6-41a7-4b0b-9f80-077b929a522e",
      "condition": {
        "counter.7000875>=": 1,
        "counter.7000863>=": 5
      },
      "result_title": "妖精的故事",
      "result_text": "这天夜里，又是月朗星疏。你原本已经睡下了，却透过窗户，隐约看到你家的庭院中似乎有人影在舞动……\n你走出房门，这才看清，那是薇的身影；它漂浮在半空中，手臂枕着头，雾气包围在周身，正舒舒服服地望着月亮。它回头望见了你，于是笑了。“来一起坐坐，主人。”它轻轻一点，你感觉自己的双脚也变轻了，似乎也可以漂浮起来……\n等到你习惯了自己的漂浮状态之后，薇又指指距离你们似乎更近了一些的月亮。“是女王大人把我们三个给封印在灯里的……这是它给我们的惩罚。”见你有些迟疑，它扳着手指数着，“除了我，还有安和留——我们三个犯了同一种罪，所以被一起流放到了这个物质世界里。”\n你说，你知道这些，毕竟，是你们把提灯从妖精的国度带了回来……\n“女王给您看到的那些，并非我们的真实面目——在无人打扰的魔法领域里，没有物质，只有精神，只有愿望……力量属于拥有最强愿望的人，愿望是一切的起点，也是终点。我们不需要肉体来被束缚在地面上，我们可以向上飞——直到我们的愿望的尽头。”它又叹了口气，而后，你和它一起向上飞了起来……再次醒来时，你依旧在自己的床上，但你的衣摆却沾满了庭院中才有的露水。",
      "result": {
        "s1+重投": 1,
        "counter+7000875": 1,
        "counter=7000863": 0,
        "counter+7000877": 1
      },
      "action": {
        "event_off": 5320638,
        "event_on": 5320646
      }
    },
    {
      "guid": "dea5a6ec-e5b3-4081-b5f3-ef6cb7dc42d4",
      "condition": {
        "counter.7000875>=": 1,
        "counter.7000863<": 5,
        "counter.7000863>=": 1
      },
      "result_title": "还不够啊……",
      "result_text": "小薇仿佛一个伤心的孩子，抱着自己的最心爱的玩具，在你的桌上打滚。“小薇还没有玩够嘛……”如果它怀里的宝贝不是一颗人的眼球，就更有说服力了……\n也许你之后可以试试满足它，毕竟，妖精是情绪的动物，当它高兴的时候，它的力量也会更强。",
      "result": {},
      "action": {}
    },
    {
      "guid": "f62bb371-5235-4b98-a9d3-d9f9fc172d69",
      "condition": {
        "counter.7000875>=": 1,
        "counter.7000863<": 1,
        "counter.7000876<": 1
      },
      "result_title": "你敷衍我，我要闹了",
      "result_text": "小薇在你的头发缝隙中打滚，它渴望着杀戮与战斗！而你完全没有满足它一点点！它就要枯萎了！你能感觉到，随着情绪的低落，妖精的力量也在降低——而且现在它还会在你与人说话的时候，不停地在袍子下面做出猥琐的形状——啊，真是糟糕透了，这些妖精。",
      "result": {
        "s1-重投": 1,
        "s1-社交": 2,
        "counter+7000876": 1
      },
      "action": {}
    }
  ],
  "settlement_extre": [
    {
      "guid": "d34f8ac7-0025-4c2a-9745-b828aaab3053",
      "condition": {
        "counter.7000876>=": 1,
        "counter.7000863>=": 1
      },
      "result_title": "再多杀一点！",
      "result_text": "妖精终于有了一些战利品——好看的眼珠子、难看的门牙、连着毛的皮肤……你终于开始认真对待薇的祝福了，它的情绪与力量也开始恢复。",
      "result": {
        "s1+重投": 1,
        "s1+社交": 2,
        "counter=7000876": 0
      },
      "action": {}
    }
  ],
  "cards_slot": {
    "s1": {
      "guid": "edd5192b-e2d5-486c-a89e-67a26905f49c",
      "condition": {
        "type": "char",
        "is": 2000432
      },
      "open_adsorb": 1,
      "is_key": 0,
      "is_empty": 0,
      "is_enemy": 0,
      "text": "它会因为情绪而变强或者捣蛋"
    }
  }
}